MANIFEST.in
README.rst
setup.py
django_hashedfilenamestorage/__init__.py
django_hashedfilenamestorage/models.py
django_hashedfilenamestorage/storage.py
django_hashedfilenamestorage/test_settings.py
django_hashedfilenamestorage/tests.py
django_hashedfilenamestorage.egg-info/PKG-INFO
django_hashedfilenamestorage.egg-info/SOURCES.txt
django_hashedfilenamestorage.egg-info/dependency_links.txt
django_hashedfilenamestorage.egg-info/requires.txt
django_hashedfilenamestorage.egg-info/top_level.txt
django_hashedfilenamestorage.egg-info/zip-safe