Metadata-Version: 1.1
Name: django-hashedfilenamestorage
Version: 2.2
Summary: A Django storage backend that names files by hash value.
Home-page: http://github.com/ecometrica/django-hashedfilenamestorage/
Author: Ecometrica
Author-email: info@ecometrica.com
License: UNKNOWN
Platform: UNKNOWN
Classifier: Development Status :: 5 - Production/Stable
Classifier: Environment :: Web Environment
Classifier: Framework :: Django
Classifier: Intended Audience :: Developers
Classifier: License :: OSI Approved :: MIT License
Classifier: Operating System :: OS Independent
Classifier: Programming Language :: Python
Classifier: Programming Language :: Python :: 2.7
Classifier: Programming Language :: Python :: 3.5
Classifier: Programming Language :: Python :: 3.6
Classifier: Topic :: Software Development :: Libraries
